kewkew/__about__.py
kewkew/__init__.py
kewkew/kew.py
kewkew-0.1.2.dist-info/METADATA
kewkew-0.1.2.dist-info/WHEEL
kewkew-0.1.2.dist-info/licenses/LICENSE
kewkew-0.1.2.dist-info/RECORD
