Metadata-Version: 2.4
Name: kewkew
Version: 0.1.2
Summary: A tiny queue library leveraging asyncio
Project-URL: Issues, https://github.com/devdupont/kewkew/issues
Project-URL: Source, https://github.com/devdupont/kewkew
Author-email: Michael duPont <michael@dupont.dev>
License-Expression: MIT
License-File: LICENSE
Classifier: License :: OSI Approved :: MIT License
Classifier: Programming Language :: Python :: 3
Classifier: Programming Language :: Python :: 3.8
Classifier: Programming Language :: Python :: 3.9
Classifier: Programming Language :: Python :: 3.10
Classifier: Programming Language :: Python :: 3.11
Classifier: Programming Language :: Python :: 3.12
Classifier: Programming Language :: Python :: 3.13
Classifier: Programming Language :: Python :: 3.14
Requires-Python: >=3.8
